behavex/__init__.py
behavex/__main__.py
behavex/arguments.py
behavex/conf_behavex.cfg
behavex/conf_logging.cfg
behavex/conf_mgr.py
behavex/environment.py
behavex/execution_singleton.py
behavex/global_vars.py
behavex/runner.py
behavex/utils.py
behavex/__pycache__/__init__.cpython-310.pyc
behavex/__pycache__/arguments.cpython-310.pyc
behavex/__pycache__/conf_mgr.cpython-310.pyc
behavex/__pycache__/environment.cpython-310.pyc
behavex/__pycache__/execution_singleton.cpython-310.pyc
behavex/__pycache__/global_vars.cpython-310.pyc
behavex/__pycache__/utils.cpython-310.pyc
behavex/outputs/__init__.py
behavex/outputs/jinja_mgr.py
behavex/outputs/output_strings.py
behavex/outputs/report_html.py
behavex/outputs/report_json.py
behavex/outputs/report_utils.py
behavex/outputs/report_xml.py
behavex/outputs/__pycache__/__init__.cpython-310.pyc
behavex/outputs/__pycache__/jinja_mgr.cpython-310.pyc
behavex/outputs/__pycache__/output_strings.cpython-310.pyc
behavex/outputs/__pycache__/report_html.cpython-310.pyc
behavex/outputs/__pycache__/report_json.cpython-310.pyc
behavex/outputs/__pycache__/report_utils.cpython-310.pyc
behavex/outputs/__pycache__/report_xml.cpython-310.pyc
behavex/outputs/bootstrap/css/behavex.css
behavex/outputs/bootstrap/css/bootstrap-theme.css
behavex/outputs/bootstrap/css/bootstrap-theme.min.css
behavex/outputs/bootstrap/css/bootstrap-theme.min.css.map
behavex/outputs/bootstrap/css/bootstrap.css
behavex/outputs/bootstrap/css/bootstrap.min.css
behavex/outputs/bootstrap/css/bootstrap.min.css.map
behavex/outputs/bootstrap/css/pace-theme-loading-bar.min.css
behavex/outputs/bootstrap/fonts/glyphicons-halflings-regular.eot
behavex/outputs/bootstrap/fonts/glyphicons-halflings-regular.svg
behavex/outputs/bootstrap/fonts/glyphicons-halflings-regular.ttf
behavex/outputs/bootstrap/fonts/glyphicons-halflings-regular.woff
behavex/outputs/bootstrap/fonts/glyphicons-halflings-regular.woff2
behavex/outputs/bootstrap/js/bootstrap.js
behavex_feature-1.0.16.dist-info/LICENSE
behavex_feature-1.0.16.dist-info/METADATA
behavex_feature-1.0.16.dist-info/WHEEL
behavex_feature-1.0.16.dist-info/entry_points.txt
behavex_feature-1.0.16.dist-info/top_level.txt
behavex_feature-1.0.16.dist-info/RECORD
