Metadata-Version: 2.1
Name: behavex-feature
Version: 1.0.16
Summary: Add support for merging multiple report
Classifier: Development Status :: 4 - Beta
Classifier: Environment :: Console
Classifier: Intended Audience :: Developers
Classifier: License :: OSI Approved :: MIT License
Classifier: Operating System :: OS Independent
Classifier: Programming Language :: Python
Classifier: Programming Language :: Python :: 3
Classifier: Programming Language :: Python :: 3.5
Classifier: Programming Language :: Python :: 3.6
Classifier: Programming Language :: Python :: 3.7
Classifier: Programming Language :: Python :: 3.8
Classifier: Programming Language :: Python :: 3.9
Classifier: Programming Language :: Python :: 3.10
Classifier: Topic :: Software Development :: Testing
Requires-Python: >=3.5
License-File: LICENSE
Requires-Dist: behave (==1.2.6)
Requires-Dist: jinja2
Requires-Dist: configobj
Requires-Dist: htmlmin
Requires-Dist: csscompressor
